{
    "subjects": [
      {
        "subject_id": "Math301",
        "subject_name": "General Math",
        "subject_title": "বাস্তব সংখ্যা",
        "chapter_number" : "1",
        "subject_url": "https://youtu.be/j2fgFlOE-k0",
        "exam_link" : "https://forms.gle/i5Xbkhhkq5BktsKTA"
      },
      {
        "subject_id": "Math302",
        "subject_name": "General Math",
        "subject_title": "সেট ও ফাংশন",
        "chapter_number" : "2",
        "subject_url": "https://youtu.be/efjR_nUVo_s",
        "exam_link" : "https://forms.gle/RfkXJwkT2tqVeqz46"
      },
      {
        "subject_id": "Math303",
        "subject_name": "General Math",
        "subject_title": "সসীম ধারা",
        "chapter_number" : "13",
        "subject_url": "https://youtu.be/a_ZX-6xsN0E",
        "exam_link" : "https://forms.gle/A2DWxnBqGuqFUR1EA"
      },
      {
        "subject_id": "Math304",
        "subject_name": "General Math",
        "subject_title": "সূচক ও লগারিদম",
        "chapter_number" : "৪",
        "subject_url": "https://youtu.be/seq-LuVi334",
        "exam_link" : "https://forms.gle/BANyZYMMcAoqU2qL9"
      },
      {
        "subject_id": "Math305",
        "subject_name": "General Math",
        "subject_title": "এক চলকবিশিষ্ট সমীকরণ",
        "chapter_number" : "5",
        "subject_url": "https://youtu.be/kXrFV5SvT_Y",
        "exam_link" : ""
      }
    ]
  }
  
  